cp2077_hash_updater-1.0.0.dist-info/licenses/LICENSE
hash_updater/__init__.py
hash_updater/cp2077_ida_build_sig_index.py
hash_updater/cp2077_ida_export_old_missing_sigs.py
hash_updater/cp2077_ida_resolve_xref_anchors_in_new.py
hash_updater/cp2077_match_missing_hashes.py
hash_updater/cp2077_merge_updates.py
hash_updater/cp2077_run_all.py
hash_updater/cp2077_update_hashes.py
hash_updater/cp2077_hashes/__init__.py
hash_updater/cp2077_hashes/address_list.py
hash_updater/cp2077_hashes/ida_signatures.py
hash_updater/cp2077_hashes/missing_log.py
hash_updater/cp2077_hashes/pe_sections.py
cp2077_hash_updater-1.0.0.dist-info/METADATA
cp2077_hash_updater-1.0.0.dist-info/WHEEL
cp2077_hash_updater-1.0.0.dist-info/entry_points.txt
cp2077_hash_updater-1.0.0.dist-info/top_level.txt
cp2077_hash_updater-1.0.0.dist-info/RECORD
