Metadata-Version: 2.4
Name: cp2077-hash-updater
Version: 1.0.0
Summary: Speedrun Cyberpunk 2077 updates
Author: alphanin9
Keywords: cp2077
Requires-Python: >=3.13
License-File: LICENSE
Requires-Dist: ida-domain>=0.3.5
Dynamic: license-file
